{
  "saludo": "Buenos días Sebastián — martes 12 May",
  "supervivencia": [
    "CAJA: 10 días críticos. EBITDA -800k. Revisar movimientos hoy",
    "EPM Río Negro: ~180M pendientes + no conformidad contrato 24 sin respuesta formal",
    "Hamilton: cobro vence hoy (deadline 2026-05-15)"
  ],
  "top_3": [
    {
      "tarea": "Revisar caja real a hoy + movimiento inversiones + plan pago Condugas",
      "categoria": "SUPERVIVENCIA",
      "porque": "10 días de caja, EBITDA negativo, necesitas visión completa",
      "tarea_id": "critica_caja_familiar"
    },
    {
      "tarea": "Enviar comunicado + programar cobro directo EPM reajustes (~180M)",
      "categoria": "SUPERVIVENCIA",
      "porque": "Dinero comprometido, contrato crítico, no puede esperar",
      "tarea_id": "cobrar_reajustes_epm"
    },
    {
      "tarea": "Base datos clientes única con necesidades + propuestas claras",
      "categoria": "ESTRATEGIA",
      "porque": "Score 47. Sin esto no sabes dónde va tu energía",
      "tarea_id": "clientes_base"
    }
  ],
  "mega_dia": "Obtener visión real de caja + iniciar cobro EPM. Si haces esto, respiras",
  "contactar_hoy": [
    {
      "persona": "Andrea",
      "motivo": "Deudas Condugas pendientes + plan pago claro"
    },
    {
      "persona": "Emanuel",
      "motivo": "Reunión rápida: estructura Siendo, roles, presupuesto"
    }
  ],
  "ojo_con": [
    "110 tareas criticas/alta sin fecha limite — asignales deadline en el calendario",
    "163 tareas vencidas — urgente priorizar",
    "Facturación sin actualizar 23 días (45% = rojo)",
    "Hamilton deadline hoy — Lina debe confirmar"
  ],
  "vencidas": [
    "Contrato 24: no conformidad sin respuesta formal",
    "Casa Aguacatala: deadline 2026-05-05 pasó"
  ],
  "frase_dia": "Hoy: caja clara + dinero en movimiento. Eso es respirar.",
  "generado_at": "2026-05-12T11:00:09",
  "fecha": "2026-05-12",
  "stats": {
    "abiertas": 209,
    "criticas": 63,
    "vencidas": 163,
    "estancadas": 192,
    "sin_evaluar": 184
  },
  "criticas_sin_fecha": [
    {
      "id": "2026-04-06-002",
      "tarea": "Recopilar información del proceso centro de operaciones",
      "prioridad": "alta",
      "responsable": "William Lopez"
    },
    {
      "id": "2026-04-08-001",
      "tarea": "Compartir informes diarios, actas de obra o correos de febrero a abril que mencionen lluvias, parada",
      "prioridad": "alta",
      "responsable": "Juan Camilo Berrio"
    },
    {
      "id": "2026-04-12-003",
      "tarea": "Conectar modelo de KPIs con el briefing para mayor claridad",
      "prioridad": "alta",
      "responsable": "Lina Russi"
    },
    {
      "id": "2026-04-12-004",
      "tarea": "Publicar documentación de KPIs en repositorio público",
      "prioridad": "alta",
      "responsable": "William Lopez"
    },
    {
      "id": "2026-04-09-004",
      "tarea": "Desarrollar ERP basado en IA",
      "prioridad": "alta",
      "responsable": "Emanuel"
    },
    {
      "id": "2026-04-13-m20be25",
      "tarea": "Resolver deudas con Condugas",
      "prioridad": "alta",
      "responsable": "Sebastian"
    },
    {
      "id": "2026-04-13-m5960dc",
      "tarea": "Situación de caja familiar , inversiones",
      "prioridad": "critica",
      "responsable": "Sebastian"
    },
    {
      "id": "2026-04-13-m35598a",
      "tarea": "Proyecto automatizaciones (App para cobra, diagnostico actual, Aleteagogia)",
      "prioridad": "alta",
      "responsable": "Sebastian"
    },
    {
      "id": "2026-04-13-me871ed",
      "tarea": "Carros, créditos, proyecciones",
      "prioridad": "alta",
      "responsable": "Sebastian"
    },
    {
      "id": "2026-04-13-m3137b0",
      "tarea": "Clientes base, iniciar por propuestas claras",
      "prioridad": "critica",
      "responsable": "Sebastian"
    },
    {
      "id": "2026-04-13-mc17d26",
      "tarea": "Unificar base de datos y fuentes Siendo Consulting",
      "prioridad": "alta",
      "responsable": "Sebastian"
    },
    {
      "id": "2026-04-14-001",
      "tarea": "Reunirse con Andrea para resolver deuda Condugas",
      "prioridad": "alta",
      "responsable": "Lina Russi"
    },
    {
      "id": "2026-04-14-006",
      "tarea": "Coordinar reunión con leads/clientes para definición estratégica",
      "prioridad": "alta",
      "responsable": "Sebastian"
    },
    {
      "id": "2026-04-14-m995aab",
      "tarea": "Estructura siendo, roles, tareas, plata, que hacer y que no hacer",
      "prioridad": "alta",
      "responsable": "Sebastian"
    },
    {
      "id": "2026-04-14-m734020",
      "tarea": "Clientes actuales para Odoo",
      "prioridad": "alta",
      "responsable": "Sebastian"
    }
  ],
  "vence_pronto": [
    {
      "id": "2026-05-06-c001",
      "tarea": "Cuantificar precisamente la brecha de reajuste (13%) en transportes y mano de obra para sustentacion",
      "dias": 1,
      "fecha_limite": "2026-05-13"
    },
    {
      "id": "2026-04-16-c001",
      "tarea": "Cobrar pago pendiente de Hamilton según lo prometido",
      "dias": 3,
      "fecha_limite": "2026-05-15"
    }
  ]
}